{
    "c_intro":null,
    "c_main":[],
    "c_pics":[],
    "c_title":"他们是亚历山大东征军后裔，隐居山谷男耕女织，过着与世隔绝生活",
    "title":"他们是亚历山大东征军后裔，隐居山谷男耕女织，过着与世隔绝生活_腾讯新闻",
    "script":"{\"type\":1,\"value\":\"\"},{\"type\":2,\"value\":\"http://inews.gtimg.com/newsapp_bt/0/10829946532/1000\",\"desc\":\"关于巴基斯坦相信很多人都有所了解，我们也经常在网上看到关于巴铁的一些帖子，巴基斯坦东北部与我国接壤，巴基斯坦是经济快速增长的发展中国家。今天小编整理了一组摄影师在巴基斯坦旅游拍摄的巴基斯坦肖像摄影作品，下面我们一起来看看吧。 (来自:手机摄影网\"},{\"type\":1,\"value\":\"\"},{\"type\":2,\"value\":\"http://inews.gtimg.com/newsapp_bt/0/10829946544/1000\",\"desc\":\"这组照片是在位于阿富汗边境附近的兴都库什山脉的卡拉什山谷拍摄的，卡拉什山谷一个古老的欧洲村庄，他们拥有独特的文化，与巴基斯坦和阿富汗人完全不同。他们的面部结构和肤色比本地人更具欧洲风味。图为巴基斯坦老妇人肖像照。 (来自:手机摄影网\"},{\"type\":1,\"value\":\"\"},{\"type\":2,\"value\":\"http://inews.gtimg.com/newsapp_bt/0/10829946535/1000\",\"desc\":\"卡拉什（Kalash）主要是异教徒，他们崇拜不同的神灵，他们过去将死者藏在地面上方的空旷坟墓中，直到尸体溶解为止。图为卡拉什山拍摄的少年肖像照。 (来自:手机摄影网\"},{\"type\":1,\"value\":\"\"},{\"type\":2,\"value\":\"http://inews.gtimg.com/newsapp_bt/0/10829946536/1000\",\"desc\":\"图为巴基斯坦卡拉什山拍摄的少女肖像照。 (来自:手机摄影网\"},{\"type\":1,\"value\":\"\"},{\"type\":2,\"value\":\"http://inews.gtimg.com/newsapp_bt/0/10829946545/1000\",\"desc\":\"图为巴基斯坦卡拉什山拍摄的男青年肖像照。 (来自:手机摄影网\"},{\"type\":1,\"value\":\"\"},{\"type\":2,\"value\":\"http://inews.gtimg.com/newsapp_bt/0/10829947004/1000\",\"desc\":\"这里的女人穿着漂亮的黑色刺绣连衣裙，上面装饰着鲜艳的彩色图案。图为穿着民族服装的少女肖像照。 (来自:手机摄影网\"},{\"type\":1,\"value\":\"\"},{\"type\":2,\"value\":\"http://inews.gtimg.com/newsapp_bt/0/10829947155/1000\",\"desc\":\"这里的人被认为是希腊马其顿亚历山大大帝东征军的后裔，生活在布姆布雷特、比里尔和鲁姆布尔三个峡谷中。图为男子肖像照。 (来自:手机摄影网\"},{\"type\":1,\"value\":\"\"},{\"type\":2,\"value\":\"http://inews.gtimg.com/newsapp_bt/0/10829947241/1000\",\"desc\":\"卡拉什人每年要庆祝3个节日：春天的乔什节，秋天的普鲁姆节和冬天的查莫斯节。特别是乔什节，由于结束了与外界隔绝的冬季，卡拉什人会身穿盛装、以隆重的活动祈求风调雨顺、五谷丰登。图为卡拉什妇女肖像照。 (来自:手机摄影网\"},{\"type\":1,\"value\":\"\"},{\"type\":2,\"value\":\"http://inews.gtimg.com/newsapp_bt/0/10829947330/1000\",\"desc\":\"图为卡拉什妇女肖像照。 (来自:手机摄影网\"},{\"type\":1,\"value\":\"\"},{\"type\":2,\"value\":\"http://inews.gtimg.com/newsapp_bt/0/10829947409/1000\",\"desc\":\"卡拉什独特的民族文化吸引了很多巴基斯坦国内外游客的到来，特别是妇女们的传统服饰，更是游客们眼中最亮丽的风景。图为卡拉什妇女肖像照。 (来自:手机摄影网\"},{\"type\":1,\"value\":\"\"},{\"type\":2,\"value\":\"http://inews.gtimg.com/newsapp_bt/0/10829947559/1000\",\"desc\":\"图为卡拉什老人肖像照。 (来自:手机摄影网\"},{\"type\":1,\"value\":\"\"},{\"type\":2,\"value\":\"http://inews.gtimg.com/newsapp_bt/0/10829947705/1000\",\"desc\":\"图为卡拉什男子肖像照。 (来自:手机摄影网\"},{\"type\":1,\"value\":\"\"},{\"type\":2,\"value\":\"http://inews.gtimg.com/newsapp_bt/0/10829947786/1000\",\"desc\":\"图为卡拉什老妇人肖像照。 (来自:手机摄影网\"},{\"type\":1,\"value\":\"\"},{\"type\":2,\"value\":\"http://inews.gtimg.com/newsapp_bt/0/10829947845/1000\",\"desc\":\"图为卡拉什儿童肖像照。 (来自:手机摄影网\"},{\"type\":1,\"value\":\"\"},{\"type\":2,\"value\":\"http://inews.gtimg.com/newsapp_bt/0/10829948039/1000\",\"desc\":\"图为卡拉什中年人肖像照。 (来自:手机摄影网\"},{\"type\":1,\"value\":\"\"},{\"type\":2,\"value\":\"http://inews.gtimg.com/newsapp_bt/0/10829948094/1000\",\"desc\":\"图为卡拉什老太太肖像照。 (来自:手机摄影网\"},{\"type\":1,\"value\":\"\"},{\"type\":2,\"value\":\"http://inews.gtimg.com/newsapp_bt/0/10835781766/1000\",\"desc\":\"每年节日期间，卡拉什妇女都会穿上这种艳丽而精美的长裙，并戴上装饰着丝线、纽扣和贝壳的头饰，让人眼前一亮。 (来自:手机摄影网\"},{\"type\":1,\"value\":\"\"},{\"type\":2,\"value\":\"http://inews.gtimg.com/newsapp_bt/0/10829948299/1000\",\"desc\":\"旅游业的繁荣给原本封闭的卡拉什村带来很多新的气息，这对卡拉什人来说或许是件好事，但对游客来说，他们希望看到是原汁原味的传统文化，而一旦这些特色沾染了别的东西，卡拉什的魅力也就不复存在了。 (来自:手机摄影网\"},{\"type\":1,\"value\":\"\"},{\"type\":2,\"value\":\"http://inews.gtimg.com/newsapp_bt/0/10829948381/1000\",\"desc\":\"图为11月初一位女子抱着孩子站在一颗老树下。 (来自:手机摄影网\"},{\"type\":1,\"value\":\"\"},{\"type\":2,\"value\":\"http://inews.gtimg.com/newsapp_bt/0/10829948629/1000\",\"desc\":\"图为卡拉什妇女穿着特色的民族服装。 (来自:手机摄影网\"}"
}